base32hex.py
xid.py
python3_xid-1.0.5.dist-info/LICENSE
python3_xid-1.0.5.dist-info/METADATA
python3_xid-1.0.5.dist-info/WHEEL
python3_xid-1.0.5.dist-info/top_level.txt
python3_xid-1.0.5.dist-info/RECORD
